{
  "transliteration": "Sfa",
  "english_glosses": [
    "to seize upon"
  ],
  "shortest_sign_count": 3,
  "difficulty_tier": "medium-easy",
  "point_value": 2,
  "primary_pos": "verb",
  "all_pos": [
    "verb"
  ],
  "sources": [
    "Vygus"
  ],
  "spellings": [
    {
      "signs": [
        "N37",
        "I9",
        "D36"
      ],
      "sign_count": 3,
      "annotated": [
        {
          "sign": "N37",
          "mnemonic": "S",
          "class": "uniliteral",
          "description": "pool"
        },
        {
          "sign": "I9",
          "mnemonic": "f",
          "class": "uniliteral",
          "description": "horned viper"
        },
        {
          "sign": "D36",
          "mnemonic": "a",
          "class": "uniliteral",
          "description": "forearm"
        }
      ]
    }
  ]
}