{
  "transliteration": "sqA / skA",
  "english_glosses": [
    "(pedestal type stone)"
  ],
  "shortest_sign_count": 3,
  "difficulty_tier": "medium-easy",
  "point_value": 2,
  "primary_pos": "noun",
  "all_pos": [
    "noun"
  ],
  "sources": [
    "Vygus"
  ],
  "spellings": [
    {
      "signs": [
        "S29",
        "N29",
        "O1"
      ],
      "sign_count": 3,
      "annotated": [
        {
          "sign": "S29",
          "mnemonic": "s",
          "class": "uniliteral",
          "description": "folded cloth"
        },
        {
          "sign": "N29",
          "mnemonic": "q",
          "class": "uniliteral",
          "description": "slope of hill"
        },
        {
          "sign": "O1",
          "mnemonic": "pr",
          "class": "biliteral",
          "description": "house"
        }
      ]
    }
  ]
}