{
  "transliteration": "tp xt",
  "english_glosses": [
    "stake"
  ],
  "shortest_sign_count": 3,
  "difficulty_tier": "medium-easy",
  "point_value": 2,
  "primary_pos": "noun",
  "all_pos": [
    "noun"
  ],
  "sources": [
    "Vygus"
  ],
  "spellings": [
    {
      "signs": [
        "D1",
        "M3",
        "M1"
      ],
      "sign_count": 3,
      "annotated": [
        {
          "sign": "D1",
          "mnemonic": "tp",
          "class": "biliteral",
          "description": "head in profile"
        },
        {
          "sign": "M3",
          "mnemonic": "xt",
          "class": "biliteral",
          "description": "branch"
        },
        {
          "sign": "M1",
          "mnemonic": "iAm",
          "class": "triliteral",
          "description": "tree"
        }
      ]
    }
  ]
}