{
  "transliteration": "Xn-Swt",
  "english_glosses": [
    "standard (of Khonsu)"
  ],
  "shortest_sign_count": 3,
  "difficulty_tier": "medium-easy",
  "point_value": 2,
  "primary_pos": "noun",
  "all_pos": [
    "noun"
  ],
  "sources": [
    "Vygus"
  ],
  "determinatives": [],
  "spellings": [
    {
      "signs": [
        "M23",
        "F26",
        "N35"
      ],
      "sign_count": 3,
      "annotated": [
        {
          "sign": "M23",
          "mnemonic": "sw",
          "class": "biliteral",
          "description": "sedge"
        },
        {
          "sign": "F26",
          "mnemonic": "Xn",
          "class": "biliteral",
          "description": "skin of goat"
        },
        {
          "sign": "N35",
          "mnemonic": "n",
          "class": "uniliteral",
          "description": "ripple of water"
        }
      ]
    }
  ]
}