{
  "transliteration": "kHss",
  "english_glosses": [
    "sedan chair",
    "a sanctuary in Edfu"
  ],
  "shortest_sign_count": 5,
  "difficulty_tier": "medium-hard",
  "point_value": 7,
  "primary_pos": "noun",
  "all_pos": [
    "noun"
  ],
  "sources": [
    "Vygus"
  ],
  "spellings": [
    {
      "signs": [
        "V31",
        "G1",
        "V28",
        "S29",
        "M3"
      ],
      "sign_count": 5,
      "annotated": [
        {
          "sign": "V31",
          "mnemonic": "k",
          "class": "uniliteral",
          "description": "basket with right handle"
        },
        {
          "sign": "G1",
          "mnemonic": "A",
          "class": "uniliteral",
          "description": "Egyptian vulture"
        },
        {
          "sign": "V28",
          "mnemonic": "H",
          "class": "uniliteral",
          "description": "wick"
        },
        {
          "sign": "S29",
          "mnemonic": "s",
          "class": "uniliteral",
          "description": "folded cloth"
        },
        {
          "sign": "M3",
          "mnemonic": "xt",
          "class": "biliteral",
          "description": "branch"
        }
      ]
    },
    {
      "signs": [
        "V31",
        "V28",
        "S29",
        "S29",
        "O1"
      ],
      "sign_count": 5,
      "annotated": [
        {
          "sign": "V31",
          "mnemonic": "k",
          "class": "uniliteral",
          "description": "basket with right handle"
        },
        {
          "sign": "V28",
          "mnemonic": "H",
          "class": "uniliteral",
          "description": "wick"
        },
        {
          "sign": "S29",
          "mnemonic": "s",
          "class": "uniliteral",
          "description": "folded cloth"
        },
        {
          "sign": "S29",
          "mnemonic": "s",
          "class": "uniliteral",
          "description": "folded cloth"
        },
        {
          "sign": "O1",
          "mnemonic": "pr",
          "class": "biliteral",
          "description": "house"
        }
      ]
    }
  ]
}