{
  "transliteration": "TmHy / tmHy",
  "english_glosses": [
    "red ochre"
  ],
  "shortest_sign_count": 5,
  "difficulty_tier": "medium-hard",
  "point_value": 7,
  "primary_pos": "noun",
  "all_pos": [
    "noun"
  ],
  "sources": [
    "Vygus"
  ],
  "spellings": [
    {
      "signs": [
        "U33",
        "G17",
        "V28",
        "M17",
        "M17"
      ],
      "sign_count": 5,
      "annotated": [
        {
          "sign": "U33",
          "mnemonic": "ti",
          "class": "biliteral",
          "description": "pestle"
        },
        {
          "sign": "G17",
          "mnemonic": "m",
          "class": "uniliteral",
          "description": "owl"
        },
        {
          "sign": "V28",
          "mnemonic": "H",
          "class": "uniliteral",
          "description": "wick"
        },
        {
          "sign": "M17",
          "mnemonic": "i",
          "class": "uniliteral",
          "description": "reed"
        },
        {
          "sign": "M17",
          "mnemonic": "i",
          "class": "uniliteral",
          "description": "reed"
        }
      ]
    }
  ]
}