{
  "transliteration": "hkrt",
  "english_glosses": [
    "female snake"
  ],
  "shortest_sign_count": 4,
  "difficulty_tier": "medium",
  "point_value": 4,
  "primary_pos": "noun",
  "all_pos": [
    "noun"
  ],
  "sources": [
    "Vygus"
  ],
  "determinatives": [
    "I14"
  ],
  "spellings": [
    {
      "signs": [
        "O4",
        "V31",
        "D21",
        "X1"
      ],
      "sign_count": 4,
      "annotated": [
        {
          "sign": "O4",
          "mnemonic": "h",
          "class": "uniliteral",
          "description": "shelter"
        },
        {
          "sign": "V31",
          "mnemonic": "k",
          "class": "uniliteral",
          "description": "basket with right handle"
        },
        {
          "sign": "D21",
          "mnemonic": "r",
          "class": "uniliteral",
          "description": "mouth"
        },
        {
          "sign": "X1",
          "mnemonic": "t",
          "class": "uniliteral",
          "description": "flat loaf"
        }
      ]
    }
  ]
}