{
  "transliteration": "qnt / kntw",
  "english_glosses": [
    "wine press"
  ],
  "shortest_sign_count": 4,
  "difficulty_tier": "medium",
  "point_value": 4,
  "primary_pos": "noun",
  "all_pos": [
    "noun"
  ],
  "sources": [
    "Vygus"
  ],
  "spellings": [
    {
      "signs": [
        "N29",
        "N35",
        "U33",
        "M17"
      ],
      "sign_count": 4,
      "annotated": [
        {
          "sign": "N29",
          "mnemonic": "q",
          "class": "uniliteral",
          "description": "slope of hill"
        },
        {
          "sign": "N35",
          "mnemonic": "n",
          "class": "uniliteral",
          "description": "ripple of water"
        },
        {
          "sign": "U33",
          "mnemonic": "ti",
          "class": "biliteral",
          "description": "pestle"
        },
        {
          "sign": "M17",
          "mnemonic": "i",
          "class": "uniliteral",
          "description": "reed"
        }
      ]
    }
  ]
}