{
  "transliteration": "SnT ib",
  "english_glosses": [
    "be angry"
  ],
  "shortest_sign_count": 4,
  "difficulty_tier": "medium",
  "point_value": 4,
  "primary_pos": "verb",
  "all_pos": [
    "verb"
  ],
  "sources": [
    "Vygus"
  ],
  "spellings": [
    {
      "signs": [
        "V7",
        "N35",
        "V13",
        "F34"
      ],
      "sign_count": 4,
      "annotated": [
        {
          "sign": "V7",
          "mnemonic": "Sn",
          "class": "biliteral",
          "description": "cord with ends downward"
        },
        {
          "sign": "N35",
          "mnemonic": "n",
          "class": "uniliteral",
          "description": "ripple of water"
        },
        {
          "sign": "V13",
          "mnemonic": "T",
          "class": "uniliteral",
          "description": "rope"
        },
        {
          "sign": "F34",
          "mnemonic": "ib",
          "class": "biliteral",
          "description": "heart"
        }
      ]
    }
  ]
}