{
  "transliteration": "bdt",
  "english_glosses": [
    "emmer",
    "var. of bdt ‘emmer’. q.v..",
    "(unknown)"
  ],
  "shortest_sign_count": 2,
  "difficulty_tier": "easy",
  "point_value": 1,
  "primary_pos": "noun",
  "all_pos": [
    "noun"
  ],
  "sources": [
    "Dickson",
    "Faulkner",
    "Vygus"
  ],
  "determinatives": [
    "H8",
    "U9"
  ],
  "spellings": [
    {
      "signs": [
        "D58",
        "X1"
      ],
      "sign_count": 2,
      "annotated": [
        {
          "sign": "D58",
          "mnemonic": "b",
          "class": "uniliteral",
          "description": "foot"
        },
        {
          "sign": "X1",
          "mnemonic": "t",
          "class": "uniliteral",
          "description": "flat loaf"
        }
      ]
    },
    {
      "signs": [
        "M34",
        "X1"
      ],
      "sign_count": 2,
      "annotated": [
        {
          "sign": "M34",
          "mnemonic": "bdt",
          "class": "triliteral",
          "description": "ear of emmer"
        },
        {
          "sign": "X1",
          "mnemonic": "t",
          "class": "uniliteral",
          "description": "flat loaf"
        }
      ]
    },
    {
      "signs": [
        "R7",
        "X1"
      ],
      "sign_count": 2,
      "annotated": [
        {
          "sign": "R7",
          "mnemonic": "snTr",
          "class": "4plus",
          "description": "bowl with smoke"
        },
        {
          "sign": "X1",
          "mnemonic": "t",
          "class": "uniliteral",
          "description": "flat loaf"
        }
      ]
    },
    {
      "signs": [
        "D58",
        "D46",
        "X1"
      ],
      "sign_count": 3,
      "annotated": [
        {
          "sign": "D58",
          "mnemonic": "b",
          "class": "uniliteral",
          "description": "foot"
        },
        {
          "sign": "D46",
          "mnemonic": "d",
          "class": "uniliteral",
          "description": "hand"
        },
        {
          "sign": "X1",
          "mnemonic": "t",
          "class": "uniliteral",
          "description": "flat loaf"
        }
      ]
    },
    {
      "signs": [
        "D58",
        "X1",
        "M34"
      ],
      "sign_count": 3,
      "annotated": [
        {
          "sign": "D58",
          "mnemonic": "b",
          "class": "uniliteral",
          "description": "foot"
        },
        {
          "sign": "X1",
          "mnemonic": "t",
          "class": "uniliteral",
          "description": "flat loaf"
        },
        {
          "sign": "M34",
          "mnemonic": "bdt",
          "class": "triliteral",
          "description": "ear of emmer"
        }
      ]
    },
    {
      "signs": [
        "M34",
        "D46",
        "X1"
      ],
      "sign_count": 3,
      "annotated": [
        {
          "sign": "M34",
          "mnemonic": "bdt",
          "class": "triliteral",
          "description": "ear of emmer"
        },
        {
          "sign": "D46",
          "mnemonic": "d",
          "class": "uniliteral",
          "description": "hand"
        },
        {
          "sign": "X1",
          "mnemonic": "t",
          "class": "uniliteral",
          "description": "flat loaf"
        }
      ]
    },
    {
      "signs": [
        "M34",
        "X1",
        "U10"
      ],
      "sign_count": 3,
      "annotated": [
        {
          "sign": "M34",
          "mnemonic": "bdt",
          "class": "triliteral",
          "description": "ear of emmer"
        },
        {
          "sign": "X1",
          "mnemonic": "t",
          "class": "uniliteral",
          "description": "flat loaf"
        },
        {
          "sign": "U10",
          "mnemonic": "it",
          "class": "biliteral",
          "description": "U9 U9 beneath M33 M33"
        }
      ]
    },
    {
      "signs": [
        "D58",
        "D46",
        "X1",
        "M34"
      ],
      "sign_count": 4,
      "annotated": [
        {
          "sign": "D58",
          "mnemonic": "b",
          "class": "uniliteral",
          "description": "foot"
        },
        {
          "sign": "D46",
          "mnemonic": "d",
          "class": "uniliteral",
          "description": "hand"
        },
        {
          "sign": "X1",
          "mnemonic": "t",
          "class": "uniliteral",
          "description": "flat loaf"
        },
        {
          "sign": "M34",
          "mnemonic": "bdt",
          "class": "triliteral",
          "description": "ear of emmer"
        }
      ]
    }
  ]
}