{
  "transliteration": "gbb",
  "english_glosses": [
    "earth",
    "Geb",
    "(a goose)"
  ],
  "shortest_sign_count": 2,
  "difficulty_tier": "easy",
  "point_value": 1,
  "primary_pos": "noun",
  "all_pos": [
    "noun"
  ],
  "sources": [
    "Dickson",
    "Faulkner",
    "Vygus"
  ],
  "spellings": [
    {
      "signs": [
        "G39",
        "D58"
      ],
      "sign_count": 2,
      "annotated": [
        {
          "sign": "G39",
          "mnemonic": "zA",
          "class": "biliteral",
          "description": "pintail"
        },
        {
          "sign": "D58",
          "mnemonic": "b",
          "class": "uniliteral",
          "description": "foot"
        }
      ]
    },
    {
      "signs": [
        "W11",
        "D58"
      ],
      "sign_count": 2,
      "annotated": [
        {
          "sign": "W11",
          "mnemonic": "nzt",
          "class": "triliteral",
          "description": "round ring stand"
        },
        {
          "sign": "D58",
          "mnemonic": "b",
          "class": "uniliteral",
          "description": "foot"
        }
      ]
    },
    {
      "signs": [
        "V33",
        "D58",
        "D58"
      ],
      "sign_count": 3,
      "annotated": [
        {
          "sign": "V33",
          "mnemonic": "sSr",
          "class": "triliteral",
          "description": "bag"
        },
        {
          "sign": "D58",
          "mnemonic": "b",
          "class": "uniliteral",
          "description": "foot"
        },
        {
          "sign": "D58",
          "mnemonic": "b",
          "class": "uniliteral",
          "description": "foot"
        }
      ]
    },
    {
      "signs": [
        "V33",
        "D58",
        "D58",
        "R8"
      ],
      "sign_count": 4,
      "annotated": [
        {
          "sign": "V33",
          "mnemonic": "sSr",
          "class": "triliteral",
          "description": "bag"
        },
        {
          "sign": "D58",
          "mnemonic": "b",
          "class": "uniliteral",
          "description": "foot"
        },
        {
          "sign": "D58",
          "mnemonic": "b",
          "class": "uniliteral",
          "description": "foot"
        },
        {
          "sign": "R8",
          "mnemonic": "nTr",
          "class": "triliteral",
          "description": "cloth on pole"
        }
      ]
    },
    {
      "signs": [
        "W11",
        "D58",
        "D58",
        "G38"
      ],
      "sign_count": 4,
      "annotated": [
        {
          "sign": "W11",
          "mnemonic": "nzt",
          "class": "triliteral",
          "description": "round ring stand"
        },
        {
          "sign": "D58",
          "mnemonic": "b",
          "class": "uniliteral",
          "description": "foot"
        },
        {
          "sign": "D58",
          "mnemonic": "b",
          "class": "uniliteral",
          "description": "foot"
        },
        {
          "sign": "G38",
          "mnemonic": "gb",
          "class": "biliteral",
          "description": "white-fronted goose"
        }
      ]
    }
  ]
}