[
  {
    "Id": {
      "Timestamp": 1613535769,
      "Machine": 16648859,
      "Pid": 19577,
      "Increment": 8112653,
      "CreationTime": "/Date(1613535769000)/"
    },
    "Transliteration": "wr-mD-",
    "GardinerSigns": "G36 M28",
    "ManuelDeCodage": "G36-M28",
    "Res": null,
    "Translations": {
      "translation": "‘<b><span style=\"color: #BF0000\">Magnate of the Ten of Upper Egypt</b></span>’, administrative title, <sup>Urk. IV, 1104, 8</sup>.",
      "TranslationMetadata": {
        "PartOfSpeech": null,
        "DictionaryName": 4,
        "Page": 95,
        "IndexOnPage": 0
      }
    }
  },
  {
    "Id": {
      "Timestamp": 1613535769,
      "Machine": 16648859,
      "Pid": 19577,
      "Increment": 8112654,
      "CreationTime": "/Date(1613535769000)/"
    },
    "Transliteration": "wr-HkAw",
    "GardinerSigns": "G36 D21 V28 D28 Z2 A40",
    "ManuelDeCodage": "G36:D21-V28-D28:Z2-A40",
    "Res": "G36:D21-V28-D28:Z1*[sep=2.0]Z1*[sep=2.0]Z1-A40",
    "Translations": {
      "translation": "‘<b><span style=\"color: #BF0000\">Great of Magic</b></span>’, ep. of gods, <sup>Pyr. 204</sup>; of king, <sup>Urk. IV, 20, 2</sup>; fem. \n <i><span style=\"color: #0070BF\">wrt-HkAw</i></span>, of goddesses, <sup>285, 13</sup>; of crowns, <sup>Les. 75, 9</sup> ( <canvas class=\"res\">S2</canvas> ); <sup>Urk. IV, 1277, 16</sup> (dets. <canvas class=\"res\">S2-S4</canvas> ); of uraeus, <sup>361, 15; 566, 2</sup> (det. <canvas class=\"res\">I13</canvas> ).",
      "TranslationMetadata": {
        "PartOfSpeech": null,
        "DictionaryName": 4,
        "Page": 95,
        "IndexOnPage": 1
      }
    }
  },
  {
    "Id": {
      "Timestamp": 1613535769,
      "Machine": 16648859,
      "Pid": 19577,
      "Increment": 8112655,
      "CreationTime": "/Date(1613535769000)/"
    },
    "Transliteration": "wr-HkAw",
    "GardinerSigns": "G36 D21 V28 D28 Z2 U19",
    "ManuelDeCodage": "G36:D21-V28-D28:Z2-U19",
    "Res": "G36:D21-V28-D28:Z1*[sep=2.0]Z1*[sep=2.0]Z1-U19",
    "Translations": {
      "translation": "<b><span style=\"color: #BF0000\">instrument for ‘Opening the Mouth’</b></span>, <sup>Ken-amūn, 61; Th. T. S. III, 35</sup>.",
      "TranslationMetadata": {
        "PartOfSpeech": null,
        "DictionaryName": 4,
        "Page": 95,
        "IndexOnPage": 2
      }
    }
  },
  {
    "Id": {
      "Timestamp": 1613535769,
      "Machine": 16648859,
      "Pid": 19577,
      "Increment": 8112656,
      "CreationTime": "/Date(1613535769000)/"
    },
    "Transliteration": "wr-",
    "GardinerSigns": "G36 D21 S42 U24",
    "ManuelDeCodage": "G36:D21-S42-U24",
    "Res": null,
    "Translations": {
      "translation": "‘<b><span style=\"color: #BF0000\">Greatest of the Master-Craftsmen</b></span>’, high-priest of Ptah at Memphis, <sup>AEO I, 38*; II, 269*</sup>.",
      "TranslationMetadata": {
        "PartOfSpeech": null,
        "DictionaryName": 4,
        "Page": 95,
        "IndexOnPage": 3
      }
    }
  },
  {
    "Id": {
      "Timestamp": 1613535769,
      "Machine": 16648859,
      "Pid": 19577,
      "Increment": 8112657,
      "CreationTime": "/Date(1613535769000)/"
    },
    "Transliteration": "wr-swnw",
    "GardinerSigns": "G36 D21 T11 W24 G43 Z3 A1",
    "ManuelDeCodage": "G36:D21-T11:(W24*G43)-Z3-A1",
    "Res": "G36:D21-T11:(W24*G43)-Z1:[sep=0.3]Z1:[sep=0.3]Z1-A1",
    "Translations": {
      "translation": "<b><span style=\"color: #BF0000\">master-physician</b></span>, <sup>ZÄS 55, 65</sup>.",
      "TranslationMetadata": {
        "PartOfSpeech": null,
        "DictionaryName": 4,
        "Page": 95,
        "IndexOnPage": 4
      }
    }
  },
  {
    "Id": {
      "Timestamp": 1613535769,
      "Machine": 16648859,
      "Pid": 19577,
      "Increment": 8112658,
      "CreationTime": "/Date(1613535769000)/"
    },
    "Transliteration": "wr-diw",
    "GardinerSigns": "G36 D21 Z1A Z1A Z1A Z1A Z1A",
    "ManuelDeCodage": "G36:D21-Z1A:Z1A:Z1A:Z1A:Z1A",
    "Res": "G36:D21-Z1a:Z1a:Z1a:Z1a:Z1a",
    "Translations": {
      "translation": "‘<b><span style=\"color: #BF0000\">Greatest of the Five</b></span>’, high-priest of Thoth at Hermopolis, \r\n <sup>ZÄS 59, 104</sup>.",
      "TranslationMetadata": {
        "PartOfSpeech": null,
        "DictionaryName": 4,
        "Page": 95,
        "IndexOnPage": 5
      }
    }
  },
  {
    "Id": {
      "Timestamp": 1613535769,
      "Machine": 16648859,
      "Pid": 19577,
      "Increment": 8112659,
      "CreationTime": "/Date(1613535769000)/"
    },
    "Transliteration": "wrt",
    "GardinerSigns": "G36 D21 X1 I12",
    "ManuelDeCodage": "G36:D21-X1-I12",
    "Res": null,
    "Translations": {
      "translation": "‘<b><span style=\"color: #BF0000\">Great One</b></span>’, ep. of uraeus, <sup>Hymnen, 10, 5</sup>; of goddesses, <sup>Sin. B64; BD \r\n 210, 12; 286, 12.15</sup>.",
      "TranslationMetadata": {
        "PartOfSpeech": null,
        "DictionaryName": 4,
        "Page": 95,
        "IndexOnPage": 6
      }
    }
  },
  {
    "Id": {
      "Timestamp": 1613535769,
      "Machine": 16648859,
      "Pid": 19577,
      "Increment": 8112660,
      "CreationTime": "/Date(1613535769000)/"
    },
    "Transliteration": "wrt",
    "GardinerSigns": "G36 D21 X1 S2",
    "ManuelDeCodage": "G36:D21-X1-S2",
    "Res": null,
    "Translations": {
      "translation": "<b><span style=\"color: #BF0000\">Crown of Upper Egypt</b></span>, <sup>Urk. IV, 244, 8</sup>.",
      "TranslationMetadata": {
        "PartOfSpeech": null,
        "DictionaryName": 4,
        "Page": 95,
        "IndexOnPage": 7
      }
    }
  },
  {
    "Id": {
      "Timestamp": 1613535769,
      "Machine": 16648859,
      "Pid": 19577,
      "Increment": 8112661,
      "CreationTime": "/Date(1613535769000)/"
    },
    "Transliteration": "wrt",
    "GardinerSigns": "G36 D21 X1 S4",
    "ManuelDeCodage": "G36:D21-X1-S4",
    "Res": null,
    "Translations": {
      "translation": "<b><span style=\"color: #BF0000\">Crown of Lower Egypt</b></span>, <sup>Pyr. 196</sup>.",
      "TranslationMetadata": {
        "PartOfSpeech": null,
        "DictionaryName": 4,
        "Page": 95,
        "IndexOnPage": 8
      }
    }
  },
  {
    "Id": {
      "Timestamp": 1613535769,
      "Machine": 16648859,
      "Pid": 19577,
      "Increment": 8112662,
      "CreationTime": "/Date(1613535769000)/"
    },
    "Transliteration": "wrt",
    "GardinerSigns": "G36 X1 P111",
    "ManuelDeCodage": "G36:X1-P111",
    "Res": null,
    "Translations": {
      "translation": "<b><span style=\"color: #BF0000\">sacred bark</b></span>, <sup>Les. 71, 18</sup>.",
      "TranslationMetadata": {
        "PartOfSpeech": null,
        "DictionaryName": 4,
        "Page": 95,
        "IndexOnPage": 9
      }
    }
  },
  {
    "Id": {
      "Timestamp": 1613535769,
      "Machine": 16648859,
      "Pid": 19577,
      "Increment": 8112663,
      "CreationTime": "/Date(1613535769000)/"
    },
    "Transliteration": "wrt",
    "GardinerSigns": "G36 X1 E1",
    "ManuelDeCodage": "G36:X1-E1",
    "Res": null,
    "Translations": {
      "translation": "<b><span style=\"color: #BF0000\">sacred cow</b></span>, <sup>Cairo 20040</sup>.",
      "TranslationMetadata": {
        "PartOfSpeech": null,
        "DictionaryName": 4,
        "Page": 95,
        "IndexOnPage": 10
      }
    }
  },
  {
    "Id": {
      "Timestamp": 1613535769,
      "Machine": 16648859,
      "Pid": 19577,
      "Increment": 8112664,
      "CreationTime": "/Date(1613535769000)/"
    },
    "Transliteration": "wri",
    "GardinerSigns": "G36 D21 M17 F51",
    "ManuelDeCodage": "G36:D21-M17-F51",
    "Res": null,
    "Translations": {
      "translation": "<b><span style=\"color: #BF0000\">portion</span> of meat</b>, <sup>Westc. 4, 15</sup>; varr. <canvas class=\"res\">G36:D21</canvas> <sup>BH I, 18</sup>;                                      \n<canvas class=\"res\">G36:D21-F51</canvas> <sup>Urk. IV, 1848, 17</sup>.",
      "TranslationMetadata": {
        "PartOfSpeech": null,
        "DictionaryName": 4,
        "Page": 95,
        "IndexOnPage": 11
      }
    }
  },
  {
    "Id": {
      "Timestamp": 1613535769,
      "Machine": 16648859,
      "Pid": 19577,
      "Increment": 8112665,
      "CreationTime": "/Date(1613535769000)/"
    },
    "Transliteration": "wryt",
    "GardinerSigns": "G36 D21 M17 M17 X1 M3 Z2",
    "ManuelDeCodage": "G36:D21-M17-M17-X1:M3:Z2",
    "Res": "G36:D21-M17-M17-X1:M3:Z1*[sep=2.0]Z1*[sep=2.0]Z1",
    "Translations": {
      "translation": "<b><span style=\"color: #BF0000\">door-posts</b></span>, <sup>Urk. IV, 520, 9</sup>.",
      "TranslationMetadata": {
        "PartOfSpeech": null,
        "DictionaryName": 4,
        "Page": 95,
        "IndexOnPage": 12
      }
    }
  },
  {
    "Id": {
      "Timestamp": 1613535769,
      "Machine": 16648859,
      "Pid": 19577,
      "Increment": 8112666,
      "CreationTime": "/Date(1613535769000)/"
    },
    "Transliteration": "wryt",
    "GardinerSigns": "G36 D21 M17 M17 X1 S28",
    "ManuelDeCodage": "G36:D21-M17-M17-X1-S28",
    "Res": null,
    "Translations": {
      "translation": "<b><span style=\"color: #BF0000\">cloth for straining liquids</b></span>, <sup>Adm. 10, 1</sup>.",
      "TranslationMetadata": {
        "PartOfSpeech": null,
        "DictionaryName": 4,
        "Page": 95,
        "IndexOnPage": 13
      }
    }
  },
  {
    "Id": {
      "Timestamp": 1613535769,
      "Machine": 16648859,
      "Pid": 19577,
      "Increment": 8112667,
      "CreationTime": "/Date(1613535769000)/"
    },
    "Transliteration": "wrmwt",
    "GardinerSigns": "G36 D21 G17 X1 G43 O36 X1 Z2",
    "ManuelDeCodage": "G36:D21-G17-X1-G43-O36-X1:Z2",
    "Res": "G36:D21-G17-X1-G43-O36-X1:Z1*[sep=2.0]Z1*[sep=2.0]Z1",
    "Translations": {
      "translation": "<b><span style=\"color: #BF0000\">roofing</b></span>, <sup>Urk. IV, 389, 11; 506, 17</sup> (det. <canvas class=\"res\">N21:Z2</canvas> ); originally <b><span style=\"color: #BF0000\">awnings</b></span>, <sup>Pyr. 2100</sup> ( <canvas class=\"res\">G36:D21-G17-X1-O169-O169-O169</canvas> ).",
      "TranslationMetadata": {
        "PartOfSpeech": null,
        "DictionaryName": 4,
        "Page": 95,
        "IndexOnPage": 14
      }
    }
  },
  {
    "Id": {
      "Timestamp": 1613535769,
      "Machine": 16648859,
      "Pid": 19577,
      "Increment": 8112668,
      "CreationTime": "/Date(1613535769000)/"
    },
    "Transliteration": "wrrt",
    "GardinerSigns": "G36 D21 D21 X1 S2",
    "ManuelDeCodage": "G36:D21-D21:X1-S2",
    "Res": null,
    "Translations": {
      "translation": "<b><span style=\"color: #BF0000\">crown</b></span>, <sup>P. Kah. 1, 3; Urk. IV, 16, 11; 255, 7</sup> (det. <canvas class=\"res\">S6</canvas> ); <sup>283, 12</sup>; as goddess, <sup>Sin.\n209</sup> (det. <canvas class=\"res\">A40</canvas> ).",
      "TranslationMetadata": {
        "PartOfSpeech": null,
        "DictionaryName": 4,
        "Page": 95,
        "IndexOnPage": 15
      }
    }
  },
  {
    "Id": {
      "Timestamp": 1613535769,
      "Machine": 16648859,
      "Pid": 19577,
      "Increment": 8112669,
      "CreationTime": "/Date(1613535769000)/"
    },
    "Transliteration": "wrryt",
    "GardinerSigns": "G36 D21 D21 M17 M17 X1 T17",
    "ManuelDeCodage": "G36:D21-D21-M17-M17-X1-T17",
    "Res": null,
    "Translations": {
      "translation": "<b><span style=\"color: #BF0000\">chariot</b></span>, <sup>Urk. IV, 615, 8; 657, 5</sup> (det. <canvas class=\"res\">M3</canvas> ); varr. <canvas class=\"res\">G36:D21-D21:X1-T17</canvas> <sup>704, 15</sup>; <canvas class=\"res\">G36:D21-M17-M17-X1-T17</canvas>\n <sup>9, 17</sup>; <canvas class=\"res\">G36:D21-X1-T17</canvas> <sup>3, 6</sup>; <canvas class=\"res\">T17-X1</canvas> <sup>1541, 12</sup>; <b><span style=\"color: #BF0000\">wagon</b></span>, <sup>RB 58, 2</sup>.",
      "TranslationMetadata": {
        "PartOfSpeech": null,
        "DictionaryName": 4,
        "Page": 95,
        "IndexOnPage": 16
      }
    }
  }
]