[
  {
    "Id": {
      "Timestamp": 1613535769,
      "Machine": 16648859,
      "Pid": 19577,
      "Increment": 8113652,
      "CreationTime": "/Date(1613535769000)/"
    },
    "Transliteration": "MDAw",
    "GardinerSigns": "G17 U28 G1 G43 N25",
    "ManuelDeCodage": "G17-U28-G1-G43-N25",
    "Res": null,
    "Translations": {
      "translation": "n. loc. <b><span style=\"color: #BF0000\">Medja</b></span>, region of Nubia, <sup>AEO I, 73*; II, 269*; ZÄS 83, 38</sup>; var. <canvas class=\"res\">G17-D36-U28-G43-T14-N25:Z2</canvas>\n <sup>Urk. IV, 142, 5</sup>.",
      "TranslationMetadata": {
        "PartOfSpeech": null,
        "DictionaryName": 4,
        "Page": 169,
        "IndexOnPage": 0
      }
    }
  },
  {
    "Id": {
      "Timestamp": 1613535769,
      "Machine": 16648859,
      "Pid": 19577,
      "Increment": 8113653,
      "CreationTime": "/Date(1613535769000)/"
    },
    "Transliteration": "MDAw",
    "GardinerSigns": "G17 U28 G1 G43 T14 A1 Z2",
    "ManuelDeCodage": "G17-U28-G1-G43-T14-A1:Z2",
    "Res": "G17-U28-G1-G43-T14-A1:Z1*[sep=2.0]Z1*[sep=2.0]Z1",
    "Translations": {
      "translation": "<b><span style=\"color: #BF0000\">Medjay</b></span>, people of Medja; later semi-military desert police, \n <sup>AEO, ZÄS locc. cit</sup>.<br>Varr. <canvas class=\"res\">G17:D36-U28-G1-M17-M17-Z7-T14-A1:Z2</canvas>\n <sup>T. Carn. 11.12;</sup> <canvas class=\"res\">D38-U28-G43-Z3</canvas> <sup>Urk. IV, 994, 17</sup>.",
      "TranslationMetadata": {
        "PartOfSpeech": null,
        "DictionaryName": 4,
        "Page": 169,
        "IndexOnPage": 1
      }
    }
  },
  {
    "Id": {
      "Timestamp": 1613535769,
      "Machine": 16648859,
      "Pid": 19577,
      "Increment": 8113654,
      "CreationTime": "/Date(1613535769000)/"
    },
    "Transliteration": "mDAb",
    "GardinerSigns": "G17 U28 Z7 D58 D40",
    "ManuelDeCodage": "G17-U28-Z7-D58-D40",
    "Res": null,
    "Translations": {
      "translation": "<b><span style=\"color: #BF0000\">expel</span> foes</b>, <sup>BD 454, 3</sup>.",
      "TranslationMetadata": {
        "PartOfSpeech": null,
        "DictionaryName": 4,
        "Page": 169,
        "IndexOnPage": 2
      }
    }
  },
  {
    "Id": {
      "Timestamp": 1613535769,
      "Machine": 16648859,
      "Pid": 19577,
      "Increment": 8113655,
      "CreationTime": "/Date(1613535769000)/"
    },
    "Transliteration": "mDAbt",
    "GardinerSigns": "G17 U28 G1 D58 X1 V30",
    "ManuelDeCodage": "G17-U28-G1-D58-X1:V30",
    "Res": null,
    "Translations": {
      "translation": "<b><span style=\"color: #BF0000\">bailer</span> of boat</b>, <sup>Urk. V, 172, 15; TR 27, 28</sup>.",
      "TranslationMetadata": {
        "PartOfSpeech": null,
        "DictionaryName": 4,
        "Page": 169,
        "IndexOnPage": 3
      }
    }
  },
  {
    "Id": {
      "Timestamp": 1613535769,
      "Machine": 16648859,
      "Pid": 19577,
      "Increment": 8113656,
      "CreationTime": "/Date(1613535769000)/"
    },
    "Transliteration": "mDAbt",
    "GardinerSigns": "G17 U28 D58 X1 D3 M3",
    "ManuelDeCodage": "G17-U28-D58-X1:D3-M3",
    "Res": null,
    "Translations": {
      "translation": "<b><span style=\"color: #BF0000\">drainer</span> for bilge</b> (?), <sup>TR 27,18</sup>. Distinct from last.",
      "TranslationMetadata": {
        "PartOfSpeech": null,
        "DictionaryName": 4,
        "Page": 169,
        "IndexOnPage": 4
      }
    }
  },
  {
    "Id": {
      "Timestamp": 1613535769,
      "Machine": 16648859,
      "Pid": 19577,
      "Increment": 8113657,
      "CreationTime": "/Date(1613535769000)/"
    },
    "Transliteration": "mDr",
    "GardinerSigns": "G17 M36 D21 O36",
    "ManuelDeCodage": "G17-M36:D21-O36",
    "Res": null,
    "Translations": {
      "translation": "<b><span style=\"color: #BF0000\">shut out</span> storms</b>, <sup>P. Kah. 2, 19</sup>; <b><span style=\"color: #BF0000\">wall in</span> treasure</b>, <sup>Urk. IV, 1087, 10</sup> \n ( <canvas class=\"res\">G17-M36:D21-M17-O36</canvas> ).",
      "TranslationMetadata": {
        "PartOfSpeech": null,
        "DictionaryName": 4,
        "Page": 169,
        "IndexOnPage": 5
      }
    }
  },
  {
    "Id": {
      "Timestamp": 1613535769,
      "Machine": 16648859,
      "Pid": 19577,
      "Increment": 8113658,
      "CreationTime": "/Date(1613535769000)/"
    },
    "Transliteration": "mDH",
    "GardinerSigns": "G17 I10 V28 V12",
    "ManuelDeCodage": "G17-I10:V28-V12",
    "Res": null,
    "Translations": {
      "translation": "<b><span style=\"color: #BF0000\">fillet</b></span>, <sup>JEA 25, 218-9</sup>; varr. <canvas class=\"res\">G17-D46-V28-V12</canvas>\n <sup>Louvre C171</sup>; <canvas class=\"res\">S10</canvas> <sup>BM 828</sup>.",
      "TranslationMetadata": {
        "PartOfSpeech": null,
        "DictionaryName": 4,
        "Page": 169,
        "IndexOnPage": 6
      }
    }
  },
  {
    "Id": {
      "Timestamp": 1613535769,
      "Machine": 16648859,
      "Pid": 19577,
      "Increment": 8113659,
      "CreationTime": "/Date(1613535769000)/"
    },
    "Transliteration": "mDHt",
    "GardinerSigns": "S10 X1",
    "ManuelDeCodage": "S10:X1",
    "Res": null,
    "Translations": {
      "translation": "<b><span style=\"color: #BF0000\">fillet</b></span> (?), <sup>Urk. IV, 38, 15</sup>.",
      "TranslationMetadata": {
        "PartOfSpeech": null,
        "DictionaryName": 4,
        "Page": 169,
        "IndexOnPage": 7
      }
    }
  },
  {
    "Id": {
      "Timestamp": 1613535769,
      "Machine": 16648859,
      "Pid": 19577,
      "Increment": 8113660,
      "CreationTime": "/Date(1613535769000)/"
    },
    "Transliteration": "mDH",
    "GardinerSigns": "S10B V28",
    "ManuelDeCodage": "S10B-V28",
    "Res": "S10b-V28",
    "Translations": {
      "translation": "<b><span style=\"color: #BF0000\">invest</span> with insignia</b>, <sup>RB 112, 4</sup>.",
      "TranslationMetadata": {
        "PartOfSpeech": null,
        "DictionaryName": 4,
        "Page": 169,
        "IndexOnPage": 8
      }
    }
  },
  {
    "Id": {
      "Timestamp": 1613535769,
      "Machine": 16648859,
      "Pid": 19577,
      "Increment": 8113661,
      "CreationTime": "/Date(1613535769000)/"
    },
    "Transliteration": "mDH",
    "GardinerSigns": "T7 V28 D40",
    "ManuelDeCodage": "T7-V28-D40",
    "Res": null,
    "Translations": {
      "translation": "<b><span style=\"color: #BF0000\">hew</span> timber</b>, <sup>RB 60, 14.16; 63, 3</sup>; <b>stone</b>, <sup>Sin. L2</sup>; <b><span style=\"color: #BF0000\">build</span> ships</b>, <sup>RB 58, 1; 60, 11</sup>.<br>Varr. <canvas class=\"res\">S10-V28-T30:D40</canvas>\n <sup>Urk. IV, 56, 13</sup>; <canvas class=\"res\">S10a:D40</canvas> <sup>98, 13;</sup> <canvas class=\"res\">G17-D38:D46-V28-T7:D40</canvas> <sup>778, 14;</sup> <canvas class=\"res\">T7</canvas> <sup>1632, 7;</sup> <canvas class=\"res\">T7:Unknown</canvas> <sup>BH I, 29</sup>.",
      "TranslationMetadata": {
        "PartOfSpeech": null,
        "DictionaryName": 4,
        "Page": 169,
        "IndexOnPage": 9
      }
    }
  },
  {
    "Id": {
      "Timestamp": 1613535769,
      "Machine": 16648859,
      "Pid": 19577,
      "Increment": 8113662,
      "CreationTime": "/Date(1613535769000)/"
    },
    "Transliteration": "mDH",
    "GardinerSigns": "T7 A1",
    "ManuelDeCodage": "T7-A1",
    "Res": null,
    "Translations": {
      "translation": "<b><span style=\"color: #BF0000\">hewer</span> of stone</b>, <sup>Munich 4, 7</sup>; <b><span style=\"color: #BF0000\">carpenter</b></span>, <sup>Cairo 20041</sup> ( <canvas class=\"res\">S10-V28</canvas> ); <sup>BM 223</sup> ( <canvas class=\"res\">S10</canvas> ); <canvas class=\"res\">F20:T7-Z1</canvas> ‘<i>head c.</i>’, <sup>BH I, 29</sup>. — N. B. <canvas class=\"res\">M23-X1:T7</canvas>\n <sup>D. el B. 108,</sup> <canvas class=\"res\">M23-X1-S10:D40</canvas> <sup>Urk. IV, 503, 13</sup> = <i><span style=\"color: #0070BF\">mDHty nsw</i></span> ‘<i>king’s unguent-maker</i>’, cf. <sup>Wb. II, 190, 11, Belegstellen</sup>.",
      "TranslationMetadata": {
        "PartOfSpeech": null,
        "DictionaryName": 4,
        "Page": 169,
        "IndexOnPage": 10
      }
    }
  },
  {
    "Id": {
      "Timestamp": 1613535769,
      "Machine": 16648859,
      "Pid": 19577,
      "Increment": 8113663,
      "CreationTime": "/Date(1613535769000)/"
    },
    "Transliteration": "mDtft",
    "GardinerSigns": "G17 I10 X1 I9 X1 U22",
    "ManuelDeCodage": "G17-I10:X1-I9:X1-U22",
    "Res": null,
    "Translations": {
      "translation": "<b><span style=\"color: #BF0000\">chisel</b></span> used in ‘<i>Opening the Mouth</i>’, <sup>JEA 18, 7, n. 1</sup>.",
      "TranslationMetadata": {
        "PartOfSpeech": null,
        "DictionaryName": 4,
        "Page": 169,
        "IndexOnPage": 11
      }
    }
  }
]