{
  "transliteration": "siAt",
  "english_glosses": [
    "encroach upon",
    "encroach upon (lands)",
    "caus. encroach upon lands",
    "fringed cloth",
    "falcon amulet",
    "to become full"
  ],
  "shortest_sign_count": 1,
  "difficulty_tier": "trivial",
  "point_value": 1,
  "primary_pos": "noun",
  "all_pos": [
    "noun",
    "verb"
  ],
  "sources": [
    "Dickson",
    "Faulkner",
    "Vygus"
  ],
  "determinatives": [
    "A2",
    "D57"
  ],
  "spellings": [
    {
      "signs": [
        "S32"
      ],
      "sign_count": 1,
      "annotated": [
        {
          "sign": "S32",
          "mnemonic": "siA",
          "class": "triliteral",
          "description": "cloth with fringe on the side"
        }
      ]
    },
    {
      "signs": [
        "S29",
        "M17",
        "G1",
        "V13"
      ],
      "sign_count": 4,
      "annotated": [
        {
          "sign": "S29",
          "mnemonic": "s",
          "class": "uniliteral",
          "description": "folded cloth"
        },
        {
          "sign": "M17",
          "mnemonic": "i",
          "class": "uniliteral",
          "description": "reed"
        },
        {
          "sign": "G1",
          "mnemonic": "A",
          "class": "uniliteral",
          "description": "Egyptian vulture"
        },
        {
          "sign": "V13",
          "mnemonic": "T",
          "class": "uniliteral",
          "description": "rope"
        }
      ]
    },
    {
      "signs": [
        "S29",
        "M17",
        "G1",
        "X1"
      ],
      "sign_count": 4,
      "annotated": [
        {
          "sign": "S29",
          "mnemonic": "s",
          "class": "uniliteral",
          "description": "folded cloth"
        },
        {
          "sign": "M17",
          "mnemonic": "i",
          "class": "uniliteral",
          "description": "reed"
        },
        {
          "sign": "G1",
          "mnemonic": "A",
          "class": "uniliteral",
          "description": "Egyptian vulture"
        },
        {
          "sign": "X1",
          "mnemonic": "t",
          "class": "uniliteral",
          "description": "flat loaf"
        }
      ]
    },
    {
      "signs": [
        "S29",
        "M17",
        "S32",
        "X1"
      ],
      "sign_count": 4,
      "annotated": [
        {
          "sign": "S29",
          "mnemonic": "s",
          "class": "uniliteral",
          "description": "folded cloth"
        },
        {
          "sign": "M17",
          "mnemonic": "i",
          "class": "uniliteral",
          "description": "reed"
        },
        {
          "sign": "S32",
          "mnemonic": "siA",
          "class": "triliteral",
          "description": "cloth with fringe on the side"
        },
        {
          "sign": "X1",
          "mnemonic": "t",
          "class": "uniliteral",
          "description": "flat loaf"
        }
      ]
    },
    {
      "signs": [
        "O34",
        "G39",
        "G1",
        "X1",
        "G39"
      ],
      "sign_count": 5,
      "annotated": [
        {
          "sign": "O34",
          "mnemonic": "z",
          "class": "uniliteral",
          "description": "bolt"
        },
        {
          "sign": "G39",
          "mnemonic": "zA",
          "class": "biliteral",
          "description": "pintail"
        },
        {
          "sign": "G1",
          "mnemonic": "A",
          "class": "uniliteral",
          "description": "Egyptian vulture"
        },
        {
          "sign": "X1",
          "mnemonic": "t",
          "class": "uniliteral",
          "description": "flat loaf"
        },
        {
          "sign": "G39",
          "mnemonic": "zA",
          "class": "biliteral",
          "description": "pintail"
        }
      ]
    },
    {
      "signs": [
        "S29",
        "M17",
        "G1",
        "X1",
        "S32"
      ],
      "sign_count": 5,
      "annotated": [
        {
          "sign": "S29",
          "mnemonic": "s",
          "class": "uniliteral",
          "description": "folded cloth"
        },
        {
          "sign": "M17",
          "mnemonic": "i",
          "class": "uniliteral",
          "description": "reed"
        },
        {
          "sign": "G1",
          "mnemonic": "A",
          "class": "uniliteral",
          "description": "Egyptian vulture"
        },
        {
          "sign": "X1",
          "mnemonic": "t",
          "class": "uniliteral",
          "description": "flat loaf"
        },
        {
          "sign": "S32",
          "mnemonic": "siA",
          "class": "triliteral",
          "description": "cloth with fringe on the side"
        }
      ]
    },
    {
      "signs": [
        "S29",
        "M17",
        "G1",
        "X1",
        "W10",
        "F18"
      ],
      "sign_count": 6,
      "annotated": [
        {
          "sign": "S29",
          "mnemonic": "s",
          "class": "uniliteral",
          "description": "folded cloth"
        },
        {
          "sign": "M17",
          "mnemonic": "i",
          "class": "uniliteral",
          "description": "reed"
        },
        {
          "sign": "G1",
          "mnemonic": "A",
          "class": "uniliteral",
          "description": "Egyptian vulture"
        },
        {
          "sign": "X1",
          "mnemonic": "t",
          "class": "uniliteral",
          "description": "flat loaf"
        },
        {
          "sign": "W10",
          "mnemonic": "iab",
          "class": "triliteral",
          "description": "cup"
        },
        {
          "sign": "F18",
          "mnemonic": "Hw",
          "class": "biliteral",
          "description": "tusk"
        }
      ]
    }
  ]
}